pysonrpc/__init__.py
pysonrpc/cli.py
pysonrpc/jsonrpc.py
pysonrpc/version.py
pysonrpc-1.0.7.dist-info/LICENSE
pysonrpc-1.0.7.dist-info/METADATA
pysonrpc-1.0.7.dist-info/WHEEL
pysonrpc-1.0.7.dist-info/entry_points.txt
pysonrpc-1.0.7.dist-info/top_level.txt
pysonrpc-1.0.7.dist-info/RECORD
