Metadata-Version: 2.1
Name: pysonrpc
Version: 1.0.7
Summary: JSON RPC Python client with autodiscovery and methods mapping
Author-email: Vivien Chene <viv@vivc.org>
Maintainer-email: Vivien Chene <viv@vivc.org>
License: MIT License
Project-URL: Homepage, https://github.com/vche/pysonrpc
Project-URL: Bug Reports, https://github.com/vche/pysonrpc/issues
Project-URL: Source, https://github.com/vche/pysonrpc
Keywords: python,json,rpc,setuptools
Classifier: Development Status :: 5 - Production/Stable
Classifier: License :: OSI Approved :: MIT License
Classifier: Programming Language :: Python :: 3
Classifier: Programming Language :: Python :: 3.10
Classifier: Programming Language :: Python :: 3.11
Classifier: Programming Language :: Python :: 3.12
Classifier: Programming Language :: Python :: 3 :: Only
Requires-Python: >=3.10
License-File: LICENSE
Requires-Dist: requests
Requires-Dist: prettytable
Provides-Extra: dev
Requires-Dist: pip ; extra == 'dev'
Requires-Dist: tox ; extra == 'dev'
Requires-Dist: build ; extra == 'dev'
Requires-Dist: codecov-cli ; extra == 'dev'
Provides-Extra: test
Requires-Dist: tox ; extra == 'test'
